dasshh/__init__.py
dasshh/__main__.py
dasshh/apps/__init__.py
dasshh/apps/general.py
dasshh/apps/os/__init__.py
dasshh/apps/os/file_operations.py
dasshh/apps/os/network_tools.py
dasshh/apps/os/process_management.py
dasshh/apps/os/system_info.py
dasshh/core/__init__.py
dasshh/core/exceptions.py
dasshh/core/logging.py
dasshh/core/registry.py
dasshh/core/runtime.py
dasshh/core/tools/__init__.py
dasshh/core/tools/base.py
dasshh/core/tools/decorator.py
dasshh/core/tools/function_tool.py
dasshh/data/__init__.py
dasshh/data/client.py
dasshh/data/models.py
dasshh/data/session.py
dasshh/ui/__init__.py
dasshh/ui/app.py
dasshh/ui/constants.py
dasshh/ui/events.py
dasshh/ui/model_provider.py
dasshh/ui/types.py
dasshh/ui/utils.py
dasshh/ui/components/__init__.py
dasshh/ui/components/navbar.py
dasshh/ui/components/chat/__init__.py
dasshh/ui/components/chat/action.py
dasshh/ui/components/chat/actions_panel.py
dasshh/ui/components/chat/chat_input.py
dasshh/ui/components/chat/chat_panel.py
dasshh/ui/components/chat/history_item.py
dasshh/ui/components/chat/history_panel.py
dasshh/ui/components/chat/message.py
dasshh/ui/components/settings/__init__.py
dasshh/ui/components/settings/checkbox.py
dasshh/ui/components/settings/dasshh_config.py
dasshh/ui/components/settings/model_config.py
dasshh/ui/components/settings/settings_section.py
dasshh/ui/screens/__init__.py
dasshh/ui/screens/help.py
dasshh/ui/screens/main.py
dasshh/ui/themes/__init__.py
dasshh/ui/themes/lime.py
dasshh/ui/views/__init__.py
dasshh/ui/views/about.py
dasshh/ui/views/chat.py
dasshh/ui/views/settings.py
dasshh-0.2.0.dist-info/licenses/LICENSE
dasshh-0.2.0.dist-info/METADATA
dasshh-0.2.0.dist-info/WHEEL
dasshh-0.2.0.dist-info/entry_points.txt
dasshh-0.2.0.dist-info/top_level.txt
dasshh-0.2.0.dist-info/RECORD
