Metadata-Version: 2.4
Name: dasshh
Version: 0.2.0
Summary: An AI Agent on your terminal, to preserve your brain juice.
Author-email: Vignesh Iyer <vgnshiyer@gmail.com>
License: MIT
Project-URL: Documentation, https://blog.vgnshiyer.dev/dasshh
Project-URL: Homepage, https://github.com/vgnshiyer/dasshh
Project-URL: Repository, https://github.com/vgnshiyer/dasshh
Project-URL: Bug Tracker, https://github.com/vgnshiyer/dasshh/issues
Requires-Python: >=3.13
License-File: LICENSE
Requires-Dist: click>=8.2.0
Requires-Dist: litellm>=1.69.3
Requires-Dist: numpydoc>=1.8.0
Requires-Dist: psutil>=7.0.0
Requires-Dist: sqlalchemy>=2.0.41
Requires-Dist: textual[syntax]>=3.2.0
Provides-Extra: dev
Requires-Dist: pytest>=7.4.0; extra == "dev"
Requires-Dist: pytest-cov>=4.1.0; extra == "dev"
Requires-Dist: pytest-asyncio>=0.21.0; extra == "dev"
Requires-Dist: mkdocs-material>=9.6.0; extra == "dev"
Dynamic: license-file
